waymo_open_dataset_tf_2_6_0-1.4.9.dist-info/METADATA
waymo_open_dataset_tf_2_6_0-1.4.9.dist-info/WHEEL
waymo_open_dataset_tf_2_6_0-1.4.9.dist-info/RECORD
waymo_open_dataset_tf_2_6_0-1.4.9.dist-info/LICENSE
waymo_open_dataset_tf_2_6_0-1.4.9.dist-info/top_level.txt
waymo_open_dataset/dataset_pb2.py
waymo_open_dataset/liblabel_cc_proto.so
waymo_open_dataset/__init__.py
waymo_open_dataset/libdataset_cc_proto.so
waymo_open_dataset/label_pb2.py
waymo_open_dataset/protos/submission_pb2.py
waymo_open_dataset/protos/libmotion_submission_cc_proto.so
waymo_open_dataset/protos/occupancy_flow_submission_pb2.py
waymo_open_dataset/protos/camera_segmentation_pb2.py
waymo_open_dataset/protos/libmap_cc_proto.so
waymo_open_dataset/protos/libsegmentation_metrics_cc_proto.so
waymo_open_dataset/protos/libcamera_segmentation_cc_proto.so
waymo_open_dataset/protos/libscenario_cc_proto.so
waymo_open_dataset/protos/libbreakdown_cc_proto.so
waymo_open_dataset/protos/motion_submission_pb2.py
waymo_open_dataset/protos/libkeypoint_cc_proto.so
waymo_open_dataset/protos/segmentation_submission_pb2.py
waymo_open_dataset/protos/__init__.py
waymo_open_dataset/protos/keypoint_pb2.py
waymo_open_dataset/protos/scenario_pb2.py
waymo_open_dataset/protos/libmetrics_cc_proto.so
waymo_open_dataset/protos/liboccupancy_flow_submission_cc_proto.so
waymo_open_dataset/protos/libmotion_metrics_cc_proto.so
waymo_open_dataset/protos/metrics_pb2.py
waymo_open_dataset/protos/libsegmentation_cc_proto.so
waymo_open_dataset/protos/libsubmission_cc_proto.so
waymo_open_dataset/protos/segmentation_pb2.py
waymo_open_dataset/protos/liboccupancy_flow_metrics_cc_proto.so
waymo_open_dataset/protos/map_pb2.py
waymo_open_dataset/protos/libsegmentation_submission_cc_proto.so
waymo_open_dataset/protos/motion_metrics_pb2.py
waymo_open_dataset/protos/segmentation_metrics_pb2.py
waymo_open_dataset/protos/occupancy_flow_metrics_pb2.py
waymo_open_dataset/protos/breakdown_pb2.py
waymo_open_dataset/common/libstatus.so
waymo_open_dataset/camera/libcamera_model.so
waymo_open_dataset/camera/__init__.py
waymo_open_dataset/camera/ops/py_camera_model_ops.py
waymo_open_dataset/camera/ops/camera_model_ops.so
waymo_open_dataset/camera/ops/__init__.py
